package_test/__init__.py
package_test/package_test.py
simple_pypi_test-1.0.0.dist-info/METADATA
simple_pypi_test-1.0.0.dist-info/WHEEL
simple_pypi_test-1.0.0.dist-info/top_level.txt
simple_pypi_test-1.0.0.dist-info/RECORD
