Metadata-Version: 2.1
Name: simple-pypi-test
Version: 1.0.0
Summary: Practicing PyPi Tools
Home-page: UNKNOWN
Author: Jihye
License: UNKNOWN
Platform: UNKNOWN
Requires-Python: >=3.8
